mockup/.jscs.json
mockup/.jshintrc
mockup/CONTRIBUTE.md
mockup/GETTING_STARTED.md
mockup/Gruntfile.js
mockup/LEARN.md
mockup/__init__.py
mockup/configure.zcml
mockup/index.html
mockup/js/config.js
mockup/js/grunt.js
mockup/js/i18n-wrapper.js
mockup/js/i18n.js
mockup/js/router.js
mockup/js/utils.js
mockup/js/bundles/docs.js
mockup/js/bundles/filemanager.js
mockup/js/bundles/plone.js
mockup/js/bundles/resourceregistry.js
mockup/js/bundles/structure.js
mockup/js/bundles/widgets.js
mockup/js/docs/app.js
mockup/js/docs/navigation.js
mockup/js/docs/page.js
mockup/js/docs/pattern.js
mockup/js/docs/view.js
mockup/js/ui/templates/dropdown.xml
mockup/js/ui/templates/popover.xml
mockup/js/ui/views/anchor.js
mockup/js/ui/views/base.js
mockup/js/ui/views/button.js
mockup/js/ui/views/buttongroup.js
mockup/js/ui/views/container.js
mockup/js/ui/views/dropdown.js
mockup/js/ui/views/popover.js
mockup/js/ui/views/toolbar.js
mockup/less/base.less
mockup/less/docs.less
mockup/less/filemanager.less
mockup/less/mixins.less
mockup/less/plone.less
mockup/less/plonelogo.less
mockup/less/plonetoolbar.less
mockup/less/popover.less
mockup/less/resourceregistry.less
mockup/less/structure.less
mockup/less/ui.less
mockup/less/widgets.less
mockup/patterns/autotoc/pattern.autotoc.less
mockup/patterns/autotoc/pattern.js
mockup/patterns/backdrop/pattern.js
mockup/patterns/base/pattern.js
mockup/patterns/contentloader/pattern.js
mockup/patterns/cookietrigger/pattern.js
mockup/patterns/datatables/pattern.datatables.less
mockup/patterns/datatables/pattern.js
mockup/patterns/eventedit/pattern.js
mockup/patterns/filemanager/pattern.filemanager.less
mockup/patterns/filemanager/pattern.js
mockup/patterns/filemanager/js/addnew.js
mockup/patterns/filemanager/js/basepopover.js
mockup/patterns/filemanager/js/customize.js
mockup/patterns/filemanager/js/delete.js
mockup/patterns/filemanager/js/findfile.js
mockup/patterns/filemanager/js/findinfiles.js
mockup/patterns/filemanager/js/newfolder.js
mockup-4.0.1.dist-info/LICENSE.rst
mockup-4.0.1.dist-info/METADATA
mockup-4.0.1.dist-info/WHEEL
mockup-4.0.1.dist-info/entry_points.txt
mockup-4.0.1.dist-info/top_level.txt
mockup-4.0.1.dist-info/RECORD
